COPYING
README.md
setup.py
cap/__init__.py
cap/../cap_build.py
py_capsicum_cffi.egg-info/PKG-INFO
py_capsicum_cffi.egg-info/SOURCES.txt
py_capsicum_cffi.egg-info/dependency_links.txt
py_capsicum_cffi.egg-info/requires.txt
py_capsicum_cffi.egg-info/top_level.txt